graffle2pdftex/__init__.py
graffle2pdftex/graffle2pdftex.applescript
graffle2pdftex/graffle2pdftex.omnijs
graffle2pdftex/graffle2pdftex.py
graffle2pdftex/omnigraffle.py
graffle2pdftex-1.0.0.5.dist-info/METADATA
graffle2pdftex-1.0.0.5.dist-info/WHEEL
graffle2pdftex-1.0.0.5.dist-info/entry_points.txt
graffle2pdftex-1.0.0.5.dist-info/top_level.txt
graffle2pdftex-1.0.0.5.dist-info/zip-safe
graffle2pdftex-1.0.0.5.dist-info/RECORD
