Metadata-Version: 2.1
Name: graffle2pdftex
Version: 1.0.0.5
Summary: A command line utility that exports omnigraffle canvases files to pdf_tex.
Home-page: https://github.com/peterjiz/graffle2pdftex
Author: Peter El-Jiz
Author-email: peter.eljiz@gmail.com
Keywords: graffle2pdftex
Classifier: Development Status :: 5 - Production/Stable
Classifier: Operating System :: MacOS :: MacOS X
Classifier: Environment :: Console
Classifier: License :: OSI Approved :: MIT License
Classifier: Programming Language :: Python :: 3.9
Classifier: Topic :: Utilities
Requires-Dist: appscript
Requires-Dist: pyobjc
Requires-Dist: PyMuPDF
